{
    "status":  "rejected",
    "error_code":  "E_STALE_SNAPSHOT",
    "message":  "based_on_read_token is missing or invalid",
    "suggestion":  "请先调用读工具获取最新 token，并仅重试一次写操作。",
    "error_message":  "based_on_read_token is missing or invalid",
    "recoverable":  true,
    "retry_policy":  {
                         "allow_auto_retry":  true,
                         "max_attempts":  1,
                         "strategy":  "refresh_read_token_then_retry_once",
                         "required_sequence":  [
                                                   "get_current_selection",
                                                   "retry_write_once"
                                               ]
                     }
}
